gh_prgen/__init__.py
gh_prgen/cli.py
gh_prgen-0.1.1.dist-info/METADATA
gh_prgen-0.1.1.dist-info/WHEEL
gh_prgen-0.1.1.dist-info/entry_points.txt
gh_prgen-0.1.1.dist-info/top_level.txt
gh_prgen-0.1.1.dist-info/RECORD
